django_intenum/__init__.py
django_intenumfield-2.0.0.dist-info/LICENSE
django_intenumfield-2.0.0.dist-info/METADATA
django_intenumfield-2.0.0.dist-info/WHEEL
django_intenumfield-2.0.0.dist-info/RECORD
