Metadata-Version: 2.1
Name: django-intenumfield
Version: 2.0.0
Summary: An IntEnumField for Django
Home-page: https://github.com/HearthSim/django-intenumfield
License: MIT
Keywords: django,intenum
Author: Jerome Leclanche
Author-email: jerome@leclan.ch
Requires-Python: >=3.8,<4.0
Classifier: License :: OSI Approved :: MIT License
Classifier: Programming Language :: Python :: 3
Classifier: Programming Language :: Python :: 3.8
Classifier: Programming Language :: Python :: 3.9
Classifier: Programming Language :: Python :: 3.10
Classifier: Programming Language :: Python :: 3.11
Classifier: Programming Language :: Python :: 3.12
Classifier: Programming Language :: Python :: 3.13
Requires-Dist: django (>=2.2)
Project-URL: Repository, https://github.com/HearthSim/django-intenumfield
